portworxapis/__init__.py
portworxapis/api/__init__.py
portworxapis/api/account_service_api.py
portworxapis/api/application_service_api.py
portworxapis/api/backup_config_service_api.py
portworxapis/api/backup_location_service_api.py
portworxapis/api/backup_policy_service_api.py
portworxapis/api/backup_service_api.py
portworxapis/api/cloud_credential_service_api.py
portworxapis/api/copilot_service_api.py
portworxapis/api/data_service_deployment_config_update_service_api.py
portworxapis/api/data_service_deployment_event_service_api.py
portworxapis/api/data_service_deployment_service_api.py
portworxapis/api/data_service_version_service_api.py
portworxapis/api/data_services_service_api.py
portworxapis/api/iam_service_api.py
portworxapis/api/image_service_api.py
portworxapis/api/invitation_service_api.py
portworxapis/api/login_service_api.py
portworxapis/api/metric_service_api.py
portworxapis/api/namespace_service_api.py
portworxapis/api/onboard_service_api.py
portworxapis/api/project_service_api.py
portworxapis/api/restore_service_api.py
portworxapis/api/service_account_service_api.py
portworxapis/api/target_cluster_registration_manifest_service_api.py
portworxapis/api/target_cluster_service_api.py
portworxapis/api/template_definition_service_api.py
portworxapis/api/template_service_api.py
portworxapis/api/tenant_service_api.py
portworxapis/api/who_am_i_service_api.py
portworxapis/api_client.py
portworxapis/api_response.py
portworxapis/configuration.py
portworxapis/exceptions.py
portworxapis/models/__init__.py
portworxapis/models/account_for_which_subscription_info_needs_to_be_updated.py
portworxapis/models/accountv1_status.py
portworxapis/models/application_health_health.py
portworxapis/models/application_phase_phase.py
portworxapis/models/application_to_be_updated.py
portworxapis/models/applicationv1_status.py
portworxapis/models/backup_config_service_create_backup_config_body.py
portworxapis/models/backup_config_service_update_backup_config_body.py
portworxapis-2024.9.4.dist-info/METADATA
portworxapis-2024.9.4.dist-info/WHEEL
portworxapis-2024.9.4.dist-info/RECORD
